{"wingAngle":0.08,"trackType":-1,"buildingDecalType":-1,"cobID":-1,"sounds":{"repair":[],"arrived":[],"underattack":[{"id":-1,"name":"warning1","volume":1}],"select":[],"deactivate":[],"activate":[],"ok":[],"cant":[{"id":-1,"name":"cantdo4","volume":1}],"working":[],"build":[]},"selfDExplosion":"mediumbuildingexplosiongenericselfd","scriptPath":"scripts/Units/ARMGUARD.cob","crashDrag":0.005,"transportSize":0,"flareSalvoDelay":0,"canAttackWater":false,"losRadius":455,"armorType":14,"power":1458.33337,"maxElevator":0.01,"canCapture":false,"tooltip":"armguard","idleAutoHeal":2.5,"trackStrength":0,"maxWeaponRange":1220,"modelname":"Units/ARMGUARD.s3o","repairable":true,"wreckName":"armguard_dead","wingDrag":0.07,"canResurrect":false,"maxHeightDif":10.717968,"maxThisUnit":32000,"levelGround":true,"trackStretch":1,"modelpath":"objects3d/Units/ARMGUARD.s3o","airLosRadius":682.5,"minWaterDepth":-10000000,"isStrafingAirUnit":false,"flareTime":90,"turnRadius":500,"kamikazeDist":0,"isBuilder":false,"extractsMetal":0,"flareReloadTime":5,"energyUpkeep":0,"radarDistance":0,"kamikazeUseLOS":false,"energyMake":0,"decloakSpherical":true,"buildDistance":128,"canDropFlare":false,"canManualFire":false,"maxDec":0,"targfac":false,"sightEmitHeight":40,"xsize":8,"springCategories":{"surface":true,"notship":true,"notair":true,"empable":true,"notland":true,"nothover":true,"all":true,"notsub":true,"weapon":true},"strafeToAttack":false,"canSelfDestruct":true,"speedToFront":0.07,"modeltype":"s3o","canGuard":true,"canRepeat":false,"showPlayerName":false,"maxPitch":0.44999999,"releaseHeld":false,"cost":1458.33337,"isHoveringAirUnit":false,"canFight":true,"decloakOnFire":true,"isFactory":false,"name":"armguard","waterline":0,"noChaseCategories":{"mobile":true},"airStrafe":true,"stealth":false,"decloakDistance":0,"tidalGenerator":0,"transportMass":100000,"buildingDecalDecaySpeed":0.1,"isTargetingUpgrade":false,"floatOnWater":false,"zsize":8,"metalCost":1250,"customParams":{"model_author":"Beherith","unitgroup":"weapon","subfolder":"armbuildings/landdefenceoffence","buildinggrounddecaltype":"decals/armguard_aoplane.dds","buildinggrounddecalsizex":"5","onoffname":"trajectory","usebuildinggrounddecal":"1","techlevel":"1","vertdisp":"6.16666651","normaltex":"unittextures/Arm_normal.dds","healthlookmod":"0","buildinggrounddecaldecayspeed":"30","buildinggrounddecalsizey":"5"},"harvestEnergyStorage":0,"trackWidth":32,"wDefs":{"193":{"shieldEnergyUse":0,"shieldPower":0,"groundbounce":false,"sprayAngle":0,"canAttackGround":true,"edgeEffectiveness":0.40000001,"accuracy":0.00522957,"noFeatureCollide":false,"fireSound":[{"id":-1,"name":"cannhvy5","volume":12.2474489}],"beamtime":1,"avoidFeature":false,"bouncerebound":1,"shieldAlpha":0.2,"size":2.75,"projectiles":1,"cylinderTargeting":0,"turret":true,"largeBeamLaser":false,"dynDamageExp":0,"waterWeapon":false,"damageAreaOfEffect":50,"sweepFire":false,"dynDamageInverted":false,"heightBoostFactor":-1,"impactOnly":false,"minIntensity":0,"gravityAffected":true,"noExplode":false,"description":"Heavy g2g long range plasma cannon","shieldRechargeDelay":0,"movingAccuracy":0.00522957,"reload":2.83333325,"craterAreaOfEffect":50,"visibleShieldRepulse":false,"fireStarter":0,"interceptedByShieldType":1,"range":1220,"shieldPowerRegenEnergy":0,"visuals":{"colorR":1,"smokeTrailCastShadow":true,"smokePeriod":8,"alwaysVisible":false,"smokeTime":60,"colorB":0,"colorG":0.5,"beamWeapon":false,"sizeDecay":0.05,"tileLength":200,"separation":1,"smokeColor":0.64999998,"smokeTrail":false,"beamDecay":1,"modelName":"","stages":8,"alphaDecay":0.91666669,"color2G":1,"smokeSize":7,"laserFlareSize":15,"thickness":2,"scrollSpeed":5,"coreThickness":0.25,"color2R":1,"pulseSpeed":1,"noGap":true,"castShadow":false,"color2B":1},"salvoSize":1,"sizeGrowth":0.5,"shieldBadColorA":1,"name":"armguard_plasma","shieldGoodColorR":0.5,"tdfId":0,"wobble":0,"selfExplode":false,"dynDamageMin":0,"noFireBaseCollide":true,"avoidFriendly":true,"weaponAcceleration":0,"targetable":0,"shieldForce":0,"stockpileTime":30,"shieldGoodColorB":1,"targetBorder":0,"visibleShieldHitFrames":0,"noNeutralCollide":false,"groundslip":1,"leadLimit":-1,"interceptSolo":true,"flightTime":0,"noAutoTarget":false,"predictBoost":0,"soundTrigger":false,"explosionSpeed":6.46716738,"shieldBadColorR":1,"duration":0.05,"shieldInterceptType":0,"leadBonus":0,"shieldRepulser":false,"proximityPriority":1,"cylinderTargetting":0,"cegTag":"arty-medium","damages":{"1":90,"2":300,"3":300,"4":90,"5":300,"6":0,"7":300,"8":300,"9":300,"10":300,"11":300,"12":300,"13":300,"14":300,"15":150,"16":90,"17":300,"0":300,"paralyzeDamageTime":0,"impulseBoost":0.123,"impulseFactor":0.5,"craterBoost":0,"craterMult":0},"shieldGoodColorG":0.5,"dance":0,"heightMod":0.80000001,"waterbounce":false,"coverageRange":0,"interceptor":0,"metalCost":0,"projectilespeed":15.000001,"highTrajectory":2,"exteriorShield":false,"customParams":[],"shieldMaxSpeed":0,"beamburst":false,"collisionSize":0.05,"shieldBadColorG":0.5,"shieldRadius":0,"isShield":false,"trajectoryHeight":0,"shieldPowerRegen":0,"startvelocity":0.01,"shieldGoodColorA":1,"noNonTargetCollide":false,"avoidNeutral":false,"noEnemyCollide":false,"paralyzer":false,"type":"Cannon","noFriendlyCollide":false,"laserHardStop":false,"tracks":false,"targetMoveError":0,"beamTTL":0,"smartShield":false,"hitSound":[{"id":-1,"name":"xplomed2","volume":12.2474489},{"id":-1,"name":"splsmed","volume":3.67423487}],"numbounce":-1,"salvoDelay":0.1,"turnRate":0,"intensity":0.2,"noSelfDamage":true,"id":193,"onlyForward":false,"dynDamageRange":1220,"myGravity":0,"uptime":0,"energyCost":0,"visibleShield":false,"stockpile":false,"manualFire":false,"shieldBadColorB":0.5,"maxAngle":0.28762141,"noGroundCollide":false},"194":{"shieldEnergyUse":0,"shieldPower":0,"groundbounce":false,"sprayAngle":0,"canAttackGround":true,"edgeEffectiveness":0.64999998,"accuracy":0.00522957,"noFeatureCollide":false,"fireSound":[{"id":-1,"name":"cannhvy5","volume":17.320509}],"beamtime":1,"avoidFeature":false,"bouncerebound":1,"shieldAlpha":0.2,"size":3.5,"projectiles":1,"cylinderTargeting":0,"turret":true,"largeBeamLaser":false,"dynDamageExp":0,"waterWeapon":false,"damageAreaOfEffect":96,"sweepFire":false,"dynDamageInverted":false,"heightBoostFactor":-1,"impactOnly":false,"minIntensity":0,"gravityAffected":true,"noExplode":false,"description":"High-trajectory g2g long-range AoE plasma cannon","shieldRechargeDelay":0,"movingAccuracy":0.00522957,"reload":7,"craterAreaOfEffect":96,"visibleShieldRepulse":false,"fireStarter":0,"interceptedByShieldType":1,"range":1220,"shieldPowerRegenEnergy":0,"visuals":{"colorR":1,"smokeTrailCastShadow":true,"smokePeriod":8,"alwaysVisible":false,"smokeTime":60,"colorB":0,"colorG":0.5,"beamWeapon":false,"sizeDecay":0.04444445,"tileLength":200,"separation":1,"smokeColor":0.64999998,"smokeTrail":false,"beamDecay":1,"modelName":"","stages":9,"alphaDecay":0.92592591,"color2G":1,"smokeSize":7,"laserFlareSize":15,"thickness":2,"scrollSpeed":5,"coreThickness":0.25,"color2R":1,"pulseSpeed":1,"noGap":true,"castShadow":false,"color2B":1},"salvoSize":1,"sizeGrowth":0.5,"shieldBadColorA":1,"name":"armguard_plasma_high","shieldGoodColorR":0.5,"tdfId":0,"wobble":0,"selfExplode":false,"dynDamageMin":0,"noFireBaseCollide":true,"avoidFriendly":true,"weaponAcceleration":0,"targetable":0,"shieldForce":0,"stockpileTime":30,"shieldGoodColorB":1,"targetBorder":0,"visibleShieldHitFrames":0,"noNeutralCollide":false,"groundslip":1,"leadLimit":-1,"interceptSolo":true,"flightTime":0,"noAutoTarget":false,"predictBoost":0,"soundTrigger":false,"explosionSpeed":6.46716738,"shieldBadColorR":1,"duration":0.05,"shieldInterceptType":0,"leadBonus":0,"shieldRepulser":false,"proximityPriority":-2,"cylinderTargetting":0,"cegTag":"arty-large","damages":{"1":90,"2":600,"3":600,"4":90,"5":600,"6":0,"7":600,"8":600,"9":600,"10":600,"11":600,"12":600,"13":600,"14":600,"15":150,"16":90,"17":600,"0":600,"paralyzeDamageTime":0,"impulseBoost":0.123,"impulseFactor":1.39999998,"craterBoost":0,"craterMult":0.096},"shieldGoodColorG":0.5,"dance":0,"heightMod":0.80000001,"waterbounce":false,"coverageRange":0,"interceptor":0,"metalCost":0,"projectilespeed":14.666667,"highTrajectory":1,"exteriorShield":false,"customParams":[],"shieldMaxSpeed":0,"beamburst":false,"collisionSize":0.05,"shieldBadColorG":0.5,"shieldRadius":0,"isShield":false,"trajectoryHeight":0,"shieldPowerRegen":0,"startvelocity":0.01,"shieldGoodColorA":1,"noNonTargetCollide":false,"avoidNeutral":false,"noEnemyCollide":false,"paralyzer":false,"type":"Cannon","noFriendlyCollide":false,"laserHardStop":false,"tracks":false,"targetMoveError":0,"beamTTL":0,"smartShield":false,"hitSound":[{"id":-1,"name":"xplomed2","volume":17.320509},{"id":-1,"name":"splslrg","volume":5.19615269}],"numbounce":-1,"salvoDelay":0.1,"turnRate":0,"intensity":0.2,"noSelfDamage":true,"id":194,"onlyForward":false,"dynDamageRange":1220,"myGravity":0,"uptime":0,"energyCost":0,"visibleShield":false,"stockpile":false,"manualFire":false,"shieldBadColorB":0.5,"maxAngle":0.28762141,"noGroundCollide":false}},"myGravity":0.40000001,"collisionVolume":{"scaleY":40,"type":"box","offsetZ":0,"defaultToPieceTree":false,"scaleX":48,"boundingRadius":39.3954315,"defaultToFootPrint":false,"defaultToSphere":false,"offsetY":-5,"scaleZ":48,"offsetX":0},"nanoColorR":0.2,"sightDistance":455,"fullHealthFactory":false,"maxAcc":0,"flankingBonusDirZ":1,"transportCapacity":0,"slideTolerance":0,"needGeo":false,"turnInPlaceSpeedLimit":0,"canAttack":true,"canBeAssisted":true,"buildingDecalSizeY":4,"canFly":false,"nanoColorB":0.2,"sonarDistanceJam":0,"canSelfD":true,"selfDCountdown":5,"isFighterAirUnit":false,"buildRange3D":false,"canAssist":false,"repairSpeed":0,"maxCoverage":0,"turnRate":0,"speed":0,"upright":true,"leaveTracks":false,"isFeature":false,"factoryHeadingTakeoff":true,"losHeight":40,"metalMake":0,"energyCost":12500,"health":3050,"isImmobile":true,"loadingRadius":220,"capturable":true,"maxWaterDepth":0,"corpse":"armguard_dead","scriptName":"scripts/Units/ARMGUARD.cob","flareDelay":0.30000001,"flankingBonusMin":1,"canSelfRepair":false,"kamikazeDistance":0,"bankingAllowed":true,"jammerRadius":0,"buildTime":21377,"verticalSpeed":3,"nanoColorG":0.69999999,"startCloaked":false,"flareDropVectorZ":0,"isGroundUnit":false,"canKamikaze":false,"highTrajectoryType":0,"activateWhenBuilt":false,"wantedHeight":0,"minCollisionSpeed":1,"collide":true,"buildingDecalSizeX":4,"totalEnergyOut":0,"cantBeTransported":true,"buildPic":"ARMGUARD.DDS","maxAileron":0.015,"harvestMetalStorage":0,"radarDistanceJam":0,"seismicSignature":0,"weapons":[{"maxAngleDif":-0.4226183,"onlyTargets":{"surface":true},"weaponDef":193,"slavedTo":0,"mainDirX":0,"badTargets":{"vtol":true},"mainDirZ":0,"mainDirY":0.99999565},{"maxAngleDif":-1,"onlyTargets":{"surface":true},"weaponDef":194,"slavedTo":0,"mainDirX":0,"badTargets":[],"mainDirZ":0.99999565,"mainDirY":0}],"sonarDistance":0,"maxBank":0.80000001,"metalStorage":0,"holdSteady":false,"isAirUnit":false,"seismicRadius":0,"canRestore":false,"flankingBonusMax":2,"armoredMultiple":1,"isStaticBuilder":false,"maxRudder":0.004,"canSubmerge":false,"seismicDistance":0,"cloakCost":0,"captureSpeed":0,"hasShield":false,"mass":1250,"sonarStealth":false,"onOffable":true,"selectionVolume":{"scaleY":69,"type":"sphere","offsetZ":0,"defaultToPieceTree":false,"scaleX":69,"boundingRadius":34.5,"defaultToFootPrint":false,"defaultToSphere":false,"offsetY":0,"scaleZ":69,"offsetX":0},"rSpeed":0,"buildOptions":[],"isBomberAirUnit":false,"useBuildingGroundDecal":false,"terraformSpeed":0,"stopToAttack":false,"reclaimable":true,"isMobileBuilder":false,"canFireControl":true,"isExtractor":false,"selfDestructCountdown":5,"flankingBonusDirY":0,"canCloak":false,"flankingBonusMode":1,"idleTime":1800,"modCategories":{"nothover":true,"notship":true,"notair":true,"empable":true,"surface":true,"notland":true,"all":true,"notsub":true,"weapon":true},"description":"armguard","showNanoFrame":true,"metalUpkeep":0,"translatedHumanName":"Gauntlet","turnInPlace":true,"hoverAttack":false,"radius":32,"fireState":-1,"cloakCostMoving":0,"flareSalvoSize":4,"canLoopbackAttack":false,"canReclaim":false,"useSmoothMesh":true,"windGenerator":0,"energyStorage":0,"flareDropVectorY":0,"sonarJamRadius":0,"buildSpeed":0,"canMove":false,"dlHoverFactor":-1,"unitFallSpeed":0,"resurrectSpeed":0,"trackOffset":0,"makesMetal":0,"model":{"midx":0,"maxz":35.5231934,"minx":-27.120165,"maxx":27.0417309,"midy":17,"textures":{"tex1":"Arm_color.dds","tex2":"Arm_other.dds"},"miny":-0.13183,"maxy":34.6520157,"midz":0,"minz":-25.277349},"height":36,"humanName":"","flankingBonusDirX":0,"maxRepairSpeed":0,"flankingBonusMobilityAdd":0.01,"radarRadius":0,"moveDef":[],"moveState":1,"buildpicname":"ARMGUARD.DDS","isBuilding":true,"isFirePlatform":false,"airSightDistance":682.5,"deathExplosion":"mediumbuildingexplosiongeneric","translatedTooltip":"Area Control Plasma Artillery","fallSpeed":0.2,"hideDamage":false,"canStockpile":false,"canRepair":false,"extractRange":0,"reclaimSpeed":0,"canParalyze":false,"transportByEnemy":true,"isTransport":false,"sonarRadius":0,"id":213,"autoHeal":0,"iconType":"armguard","frontToSpeed":0.1,"flareDropVectorX":0,"flareEfficiency":0.5,"showNanoSpray":true,"radarEmitHeight":40,"upDirSmoothing":0,"cruiseAltitude":0,"canPatrol":true,"transportUnloadMethod":0}